abraham.py
setup.py
abraham.egg-info/PKG-INFO
abraham.egg-info/SOURCES.txt
abraham.egg-info/dependency_links.txt
abraham.egg-info/top_level.txt